toastCE/__init__.py
toastce-0.1.2.dist-info/METADATA
toastce-0.1.2.dist-info/WHEEL
toastce-0.1.2.dist-info/top_level.txt
toastce-0.1.2.dist-info/RECORD
