Metadata-Version: 2.4
Name: toastCE
Version: 0.1.2
Summary: A easy and simple way to make custom exceptions.
Author: toasta (toastman32)
Author-email: toastman32@toastreal.xyz
Classifier: Programming Language :: Python :: 3
Classifier: License :: OSI Approved :: MIT License
Requires-Python: >=3.7
Dynamic: author
Dynamic: author-email
Dynamic: classifier
Dynamic: requires-python
Dynamic: summary
